Metadata-Version: 2.1
Name: uropa
Version: 3.5.3
Summary: UROPA is a command line based tool, intended for genomic region annotation
Home-page: https://github.molgen.mpg.de/loosolab/UROPA
Author: Jens Preussner
Author-email: jens.preussner@mpi-bn.mpg.de
License: MIT
Platform: UNKNOWN
Classifier: License :: OSI Approved :: MIT License
Classifier: Intended Audience :: Science/Research
Classifier: Topic :: Scientific/Engineering :: Bio-Informatics
Classifier: Programming Language :: Python 
